pyHalo/__init__.py
pyHalo/concentration_models.py
pyHalo/defaults.py
pyHalo/mass_function_models.py
pyHalo/plotting_routines.py
pyHalo/preset_models.py
pyHalo/pyhalo.py
pyHalo/realization_extensions.py
pyHalo/single_realization.py
pyHalo/truncation_models.py
pyHalo/utilities.py
pyHalo/Cosmology/__init__.py
pyHalo/Cosmology/cosmology.py
pyHalo/Cosmology/geometry.py
pyHalo/GalacticusInterface/__init__.py
pyHalo/GalacticusInterface/param_file.py
pyHalo/GalacticusInterface/read_output.py
pyHalo/Halos/__init__.py
pyHalo/Halos/accretion.py
pyHalo/Halos/concentration.py
pyHalo/Halos/halo_base.py
pyHalo/Halos/lens_cosmo.py
pyHalo/Halos/tidal_truncation.py
pyHalo/Halos/tnfw_halo_util.py
pyHalo/Halos/HaloModels/NFW.py
pyHalo/Halos/HaloModels/NFW_core.py
pyHalo/Halos/HaloModels/NFW_core_trunc.py
pyHalo/Halos/HaloModels/PsuedoJaffe.py
pyHalo/Halos/HaloModels/TNFW.py
pyHalo/Halos/HaloModels/TNFWFromParams.py
pyHalo/Halos/HaloModels/TNFWemulator.py
pyHalo/Halos/HaloModels/ULDM.py
pyHalo/Halos/HaloModels/__init__.py
pyHalo/Halos/HaloModels/blackhole.py
pyHalo/Halos/HaloModels/gaussianhalo.py
pyHalo/Halos/HaloModels/generalized_nfw.py
pyHalo/Halos/HaloModels/powerlaw.py
pyHalo/Halos/HaloModels/prompt_cusp.py
pyHalo/Halos/HaloModels/sis.py
pyHalo/Halos/galacticus_truncation/__init__.py
pyHalo/Halos/galacticus_truncation/interp_mass_loss.py
pyHalo/Halos/galacticus_truncation/johnsonSUparams.py
pyHalo/Halos/galacticus_truncation/johnsonSUparams_host_scatter.py
pyHalo/Halos/galacticus_truncation/johnsonSUparams_no_host_scatter.py
pyHalo/Halos/galacticus_truncation/tabulated_mass_loss_Keeley24.py
pyHalo/Halos/galacticus_truncation/transfer_function_density_profile.py
pyHalo/Halos/galacticus_util/__init__.py
pyHalo/Halos/galacticus_util/galacticus_filter.py
pyHalo/Halos/galacticus_util/galacticus_util.py
pyHalo/PresetModels/__init__.py
pyHalo/PresetModels/cdm.py
pyHalo/PresetModels/external.py
pyHalo/PresetModels/mbh.py
pyHalo/PresetModels/sidm.py
pyHalo/PresetModels/uldm.py
pyhalo-1.4.3.dist-info/AUTHORS.rst
pyhalo-1.4.3.dist-info/LICENSE
pyhalo-1.4.3.dist-info/METADATA
pyhalo-1.4.3.dist-info/WHEEL
pyhalo-1.4.3.dist-info/entry_points.txt
pyhalo-1.4.3.dist-info/top_level.txt
pyhalo-1.4.3.dist-info/RECORD
