Metadata-Version: 2.1
Name: pyhalo
Version: 1.4.3
Summary: A python package for generating populations of dark matter halos
Home-page: https://github.com/dangilman/pyHalo
Author: Daniel Gilman
Author-email: Daniel Gilman <gilmanda@uchicago.edu>
License: MIT license
Project-URL: Homepage, https://github.com/dangilman/pyHalo
Project-URL: Bug Tracker, https://github.com/dangilman/pyHalo/issues
Keywords: pyHalo
Classifier: Programming Language :: Python :: 3
Classifier: License :: OSI Approved :: MIT License
Classifier: Operating System :: OS Independent
Requires-Python: >=3.8
License-File: LICENSE
License-File: AUTHORS.rst
Requires-Dist: Click>=6.0
